{
	"ServerList": [{
			"Id": 1,
			"Url": "http://192.168.2.150:4568/Toba/GMServers",
			"Name": "送审服",
			"Servers":[{
					"Name":"agentd_001",
					"Type":1
				},{
					"Name":"center_001",
					"Type":2
				},{
					"Name":"LOGINSERVER_001",
					"Type":3
				},{
					"Name":"WORLDSERVER_001",
					"Type":4
				},{
					"Name":"MATCHSERVER_001",
					"Type":5
				},{
					"Name":"BATTLESERVER_001",
					"Type":6
				}]
		},{
			"Id": 2,
			"Url": "http://192.168.2.150:4568/Toba/GMServers",
			"Name": "龙龙",
			"Servers":[{
					"Name":"agentd_001",
					"Type":1
				},{
					"Name":"center_001",
					"Type":2
				},{
					"Name":"LOGINSERVER_001",
					"Type":3
				},{
					"Name":"WORLDSERVER_001",
					"Type":4
				},{
					"Name":"MATCHSERVER_001",
					"Type":5
				},{
					"Name":"BATTLESERVER_001",
					"Type":6
				}]
		}]
}
